nonebot_plugin_requests/__init__.py
nonebot_plugin_requests/config.py
nonebot_plugin_requests/requests.py
nonebot_plugin_requests-0.1.4.dist-info/LICENSE
nonebot_plugin_requests-0.1.4.dist-info/METADATA
nonebot_plugin_requests-0.1.4.dist-info/WHEEL
nonebot_plugin_requests-0.1.4.dist-info/RECORD
