Metadata-Version: 2.1
Name: nonebot-plugin-requests
Version: 0.1.4
Summary: 
Author: Ailitonia
Author-email: 41713304+Ailitonia@users.noreply.github.com
Requires-Python: >=3.10,<4.0
Classifier: Programming Language :: Python :: 3
Classifier: Programming Language :: Python :: 3.10
Classifier: Programming Language :: Python :: 3.11
Classifier: Programming Language :: Python :: 3.12
Provides-Extra: ujson
Requires-Dist: nonebot2[aiohttp,fastapi,httpx,websockets] (>=2.3.1)
Requires-Dist: ujson (>=5.8.0,<6.0.0) ; extra == "ujson"
